plane_env/__init__.py
plane_env/agent.py
plane_env/agent_gym.py
plane_env/dynamics.py
plane_env/env.py
plane_env/env_gymnasium.py
plane_env/env_jax.py
plane_env/rendering.py
plane_env/runner.py
plane_env/utils.py
plane_env-0.1.3.1.dist-info/METADATA
plane_env-0.1.3.1.dist-info/WHEEL
plane_env-0.1.3.1.dist-info/RECORD
