Metadata-Version: 2.1
Name: plane-env
Version: 0.1.3.1
Summary: A reinforcement learning environment for simulating a plane in 2D available, with gymnasium and gymnax support
Home-page: https://github.com/yannberthelot/Plane
Keywords: reinforcement-learning,gymnasium,jax,airplane,simulation
Author: Yann Berthelot
Author-email: yannberthelot1@gmail.com
Requires-Python: >=3.10,<3.13
Classifier: Development Status :: 3 - Alpha
Classifier: Intended Audience :: Science/Research
Classifier: License :: OSI Approved :: MIT License
Classifier: Programming Language :: Python :: 3
Classifier: Programming Language :: Python :: 3.10
Classifier: Programming Language :: Python :: 3.11
Classifier: Programming Language :: Python :: 3.12
Classifier: Topic :: Scientific/Engineering :: Artificial Intelligence
Requires-Dist: distrax (>=0.1.5,<0.2.0)
Requires-Dist: gymnasium (>=1.2.0,<2.0.0)
Requires-Dist: gymnax (>=0.0.9,<0.0.10)
Requires-Dist: jax (<7.0)
Requires-Dist: matplotlib (>=3.8.1,<4.0.0)
Requires-Dist: moviepy (>=2.2.1,<3.0.0)
Requires-Dist: numpy (>=1.26.1,<2.0.0)
Requires-Dist: pygame (>=2.6.1,<3.0.0)
Requires-Dist: six (>=1.16.0,<2.0.0)
Project-URL: Repository, https://github.com/yannberthelot/Plane
